cfun/__init__.py
cfun/data/__init__.py
cfun/data/frequency.csv
cfun/font.py
cfun/freq.py
cfun/imgclean.py
cfun/json.py
cfun/md5.py
cfun/phrase.py
cfun/read.py
cfun/sfz/__init__.py
cfun/sfz/idcardocr.py
cfun/utils/AES.py
cfun/utils/__init__.py
cfun/utils/downimg.py
cfun/yolo/__init__.py
cfun/yolo/base.py
cfun/yolo/classify.py
cfun/yolo/convert.py
cfun/yolo/detclsonnx.py
cfun/yolo/detclspt.py
cfun/yolo/detect.py
cfun/yolo/makechar.py
cfun/yolo/splitdata.py
cfun/yolo/xlabel.py
cfun/yzm/__init__.py
cfun/yzm/chaojiying.py
cfun/yzm/dddocrtool.py
cfun-0.5.7.dist-info/WHEEL
cfun-0.5.7.dist-info/entry_points.txt
cfun-0.5.7.dist-info/METADATA
cfun-0.5.7.dist-info/RECORD
