Metadata-Version: 2.3
Name: cfun
Version: 0.5.7
Summary: my function library
Author: zoushucai
Author-email: zoushucai <zoushucai@users.noreply.github.com>
Requires-Dist: char-similar-z>=0.2.0
Requires-Dist: pandas>=1.5.0
Requires-Dist: requests>=2.0.0
Requires-Dist: pillow>=10.0.0
Requires-Dist: opencv-python>=4.5.0
Requires-Dist: jsonpath>=0.6.0
Requires-Dist: onnx>=1.18.0
Requires-Dist: py3-wget>=1.0.0
Requires-Dist: tenacity>=8.1.0
Requires-Dist: pypinyin>=0.54.0
Requires-Dist: pycryptodome>=3.23.0
Requires-Python: >=3.10
Project-URL: Changelog, https://github.com/zoushucai/cfun/blob/main/CHANGELOG.md
Project-URL: Documentation, https://cfun.readthedocs.org
Project-URL: Homepage, https://github.com/zoushucai/cfun
Project-URL: Issues, https://github.com/zoushucai/cfun/issues
Project-URL: Repository, https://github.com/zoushucai/cfun.git
